sam_ml/__init__.py
sam_ml/config/__init__.py
sam_ml/config/global_variables.py
sam_ml/config/logging.py
sam_ml/data/__init__.py
sam_ml/data/main_data.py
sam_ml/data/preprocessing/__init__.py
sam_ml/data/preprocessing/embeddings.py
sam_ml/data/preprocessing/feature_selection.py
sam_ml/data/preprocessing/sampling.py
sam_ml/data/preprocessing/sampling_pipeline.py
sam_ml/data/preprocessing/scaler.py
sam_ml/data/regio/__init__.py
sam_ml/data/regio/mapping.py
sam_ml/data/regio/plz-5stellig.dbf
sam_ml/data/regio/plz-5stellig.prj
sam_ml/data/regio/plz-5stellig.shp
sam_ml/data/regio/plz-5stellig.shx
sam_ml/data/regio/visualisation.py
sam_ml/data/regio/zuordnung_plz_ort.csv
sam_ml/models/__init__.py
sam_ml/models/main_auto_ml.py
sam_ml/models/main_classifier.py
sam_ml/models/main_model.py
sam_ml/models/main_pipeline.py
sam_ml/models/main_regressor.py
sam_ml/models/microwave_finish_sound.mp3
sam_ml/models/scorer.py
sam_ml/models/automl/ClassifierTest.py
sam_ml/models/automl/RegressorTest.py
sam_ml/models/automl/__init__.py
sam_ml/models/classifier/AdaBoostClassifier.py
sam_ml/models/classifier/BaggingClassifier.py
sam_ml/models/classifier/BernoulliNB.py
sam_ml/models/classifier/DecisionTreeClassifier.py
sam_ml/models/classifier/ExtraTreesClassifier.py
sam_ml/models/classifier/GaussianNB.py
sam_ml/models/classifier/GaussianProcessClassifier.py
sam_ml/models/classifier/GradientBoostingMachine.py
sam_ml/models/classifier/KNeighborsClassifier.py
sam_ml/models/classifier/LinearDiscriminantAnalysis.py
sam_ml/models/classifier/LinearSupportVectorClassifier.py
sam_ml/models/classifier/LogisticRegression.py
sam_ml/models/classifier/MLPClassifier.py
sam_ml/models/classifier/QuadraticDiscriminantAnalysis.py
sam_ml/models/classifier/RandomForestClassifier.py
sam_ml/models/classifier/SupportVectorClassifier.py
sam_ml/models/classifier/XGBoostClassifier.py
sam_ml/models/classifier/__init__.py
sam_ml/models/regressor/BayesianRidge.py
sam_ml/models/regressor/DecisionTreeRegressor.py
sam_ml_py-1.3.0.dist-info/LICENSE
sam_ml_py-1.3.0.dist-info/METADATA
sam_ml_py-1.3.0.dist-info/WHEEL
sam_ml_py-1.3.0.dist-info/top_level.txt
sam_ml_py-1.3.0.dist-info/RECORD
