Metadata-Version: 2.1
Name: sam-ml-py
Version: 1.3.0
Summary: a library for ML programing created by Samuel Brinkmann
Author: Samuel Brinkmann
License: MIT
Requires-Python: >=3.10
License-File: LICENSE
Requires-Dist: scikit-learn
Requires-Dist: pandas
Requires-Dist: matplotlib
Requires-Dist: numpy
Requires-Dist: imbalanced-learn
Requires-Dist: pygame
Requires-Dist: ipywidgets
Requires-Dist: tqdm
Requires-Dist: statsmodels
Requires-Dist: sentence-transformers
Requires-Dist: xgboost
Requires-Dist: ConfigSpace
Requires-Dist: geopandas
Provides-Extra: test
Requires-Dist: pytest ; extra == 'test'
Requires-Dist: pylint ; extra == 'test'
Requires-Dist: isort ; extra == 'test'
Requires-Dist: refurb ; extra == 'test'
Requires-Dist: black ; extra == 'test'
Provides-Extra: with_swig
Requires-Dist: smac ; extra == 'with_swig'
